MANIFEST.in
setup.py
carpentry/__init__.py
carpentry/cli.py
carpentry/conf.py
carpentry/models.py
carpentry/registry.py
carpentry/routes.py
carpentry/server.py
carpentry/util.py
carpentry/version.py
carpentry/wsgi.py
carpentry/api/__init__.py
carpentry/api/core.py
carpentry/api/resources.py
carpentry/static/404.html
carpentry/static/500.html
carpentry/static/css/ansi.css
carpentry/static/css/buildbottv.css
carpentry/static/css/carpentry-icon-96.png
carpentry/static/css/carpentry-icon.png
carpentry/static/css/carpentry.css
carpentry/static/css/fullscreen.css
carpentry/static/css/paper.css
carpentry/static/css/tango.css
carpentry/static/img/android-icon-144x144.png
carpentry/static/img/android-icon-192x192.png
carpentry/static/img/android-icon-36x36.png
carpentry/static/img/android-icon-48x48.png
carpentry/static/img/android-icon-72x72.png
carpentry/static/img/android-icon-96x96.png
carpentry/static/img/apple-icon-114x114.png
carpentry/static/img/apple-icon-120x120.png
carpentry/static/img/apple-icon-144x144.png
carpentry/static/img/apple-icon-152x152.png
carpentry/static/img/apple-icon-180x180.png
carpentry/static/img/apple-icon-57x57.png
carpentry/static/img/apple-icon-60x60.png
carpentry/static/img/apple-icon-72x72.png
carpentry/static/img/apple-icon-76x76.png
carpentry/static/img/apple-icon-precomposed.png
carpentry/static/img/apple-icon.png
carpentry/static/img/browserconfig.xml
carpentry/static/img/docker-logo.png
carpentry/static/img/favicon-16x16.png
carpentry/static/img/favicon-32x32.png
carpentry/static/img/favicon-96x96.png
carpentry/static/img/favicon.ico
carpentry/static/img/manifest.json
carpentry/static/img/ms-icon-144x144.png
carpentry/static/img/ms-icon-150x150.png
carpentry/static/img/ms-icon-310x310.png
carpentry/static/img/ms-icon-70x70.png
carpentry/static/img/navbar-logo.png
carpentry/static/js/app.0.common.js
carpentry/static/js/app.0.models.js
carpentry/static/js/app.1.auth.js
carpentry/static/js/app.10.userprofile.js
carpentry_ci.egg-info/PKG-INFO
carpentry_ci.egg-info/SOURCES.txt
carpentry_ci.egg-info/dependency_links.txt
carpentry_ci.egg-info/entry_points.txt
carpentry_ci.egg-info/not-zip-safe
carpentry_ci.egg-info/requires.txt
carpentry_ci.egg-info/top_level.txt