Metadata-Version: 1.0
Name: carpentry-ci
Version: 0.3.0
Summary: continuous integration for the people
Home-page: http://falcao.it/carpentry
Author: Gabriel Falcao
Author-email: gabriel@nacaolivre.org
License: UNKNOWN
Platform: UNKNOWN
